[
  {
    "id": "tax_officer",
    "name": "Galactic Tax Officer",
    "sprite": "tax_officer.png",
    "text": "Supreme overlord, we can quietly increase taxation on your subjects this cycle.",
    "conditions": {
      "minCoins": 0
    },
    "options": [
      {
        "id": "raise_taxes",
        "text": "Yes. Squeeze them a little.",
        "effects": {
          "coins": 75,
          "happiness": -10,
          "taxRateDelta": 0.02,
          "rebellionDelta": 5
        },
        "reaction": "Your wish is my command, my lord. The ledgers will bleed with new revenue."
      },
      {
        "id": "decline_taxes",
        "text": "No. Let them breathe.",
        "effects": {
          "happiness": 5,
          "rebellionDelta": -2
        },
        "reaction": "As you decree. The scribes will stand down and the people will whisper your mercy."
      }
    ]
  },
  {
    "id": "angry_citizen_high_tax",
    "name": "Angry Citizen",
    "sprite": "citizen.png",
    "text": "The tax rates are far too high, overlord! We can barely survive.",
    "conditions": {
      "minTaxRate": 0.2
    },
    "options": [
      {
        "id": "lower_taxes_a_bit",
        "text": "Fine. Ease the burden slightly.",
        "effects": {
          "taxRateDelta": -0.02,
          "happiness": 10,
          "rebellionDelta": -10
        },
        "reaction": "Th-thank you, my lord. Maybe we can see our children eat again."
      },
      {
        "id": "refuse_to_lower",
        "text": "No. The empire needs every coin.",
        "effects": {
          "happiness": -10,
          "rebellionDelta": 10
        },
        "reaction": "Wha-no... please! You will squeeze us until we break."
      }
    ]
  },
  {
    "id": "merchant",
    "name": "Shady Merchant",
    "sprite": "merchant.png",
    "text": "Overlord, I can sell you rare artifacts from distant worlds.",
    "conditions": {
      "minCoins": 50
    },
    "options": [
      {
        "id": "buy_artifacts",
        "text": "Buy the artifacts.",
        "effects": {
          "coins": -50,
          "happiness": 10
        },
        "reaction": "A pleasure doing business, overlord. These trinkets will dazzle your court."
      },
      {
        "id": "refuse_merchant",
        "text": "Refuse. This smells like a scam.",
        "effects": {
          "happiness": -5
        },
        "reaction": "Tch. You wound me, my lord. May your vault never know true wonder."
      }
    ]
  },
  {
    "id": "space_wizard",
    "name": "Void Wizard",
    "sprite": "space_wizard.png",
    "text": "Overlord... care to take a gamble with the currents of fate?",
    "conditions": {
      "minCoins": 10
    },
    "options": [
      {
        "id": "wizard_gamble_yes",
        "text": "Yes. I welcome fortune or ruin.",
        "effects": {
          "special": "wizard_gamble"
        },
        "reaction": "Excellent. The void stirs. Let us see whom it favors today."
      },
      {
        "id": "wizard_gamble_no",
        "text": "No. I do not trust cosmic dice.",
        "effects": {
          "happiness": 2
        },
        "reaction": "Caution is a cage and a shield, overlord. The void will wait for another day."
      }
    ]
  },
  {
    "id": "bandit_hunter",
    "name": "Bounty Huntress",
    "sprite": "bandit_huntress.png",
    "text": "Overlord, a criminal wreaks havoc on your subjects. Pay me and I will hunt them down.",
    "conditions": {
      "minCoins": 0
    },
    "options": [
      {
        "id": "hire_bandit_hunter",
        "text": "Hire her to hunt the criminal.",
        "effects": {
          "special": "start_bandit_contract"
        },
        "reaction": "Your quarry is mine, my lord. I will bring you news one way or another."
      },
      {
        "id": "ignore_criminal",
        "text": "Let the criminal roam. It is beneath my concern.",
        "effects": {
          "happiness": -15,
          "rebellionDelta": 10
        },
        "reaction": "Then your people will bleed in the streets, not on my blade. Remember that choice."
      }
    ]
  },
  {
    "id": "prophet",
    "name": "Veiled Prophet",
    "sprite": "prophet.png",
    "text": "For a small offering, I will peer into the mood of your subjects.",
    "conditions": {
      "minCoins": 20,
      "minRebellionChance": 20
    },
    "options": [
      {
        "id": "pay_prophet",
        "text": "Pay her to read the currents.",
        "effects": {
          "coins": -30,
          "special": "prophet_pay"
        },
        "reaction": "The veil parts for those who pay the price. Listen carefully to what I reveal next."
      },
      {
        "id": "dismiss_prophet",
        "text": "I do not need omens.",
        "effects": {
          "happiness": -3
        },
        "reaction": "Then walk blind among storms, overlord. The fates will not soften your fall."
      }
    ]
  },
  {
    "id": "tax_collector",
    "name": "Imperial Tax Collector",
    "sprite": "tax_collector.png",
    "text": "Overlord, your citizens have paid their taxes. These funds are now yours.",
    "conditions": {
      "minCoins": 0
    },
    "options": [
      {
        "id": "accept_taxes",
        "text": "Excellent. Add it to the treasury.",
        "effects": {
          "special": "tax_collector"
        },
        "reaction": "At once, my lord. The coffers will gleam with the sweat of your subjects."
      }
    ]
  },
  {
    "id": "refugee_fleet",
    "name": "Refugee Fleet",
    "sprite": "refugees.png",
    "text": "Overlord, a fleet of displaced aliens seeks shelter in your territory.",
    "conditions": {
      "minCoins": 30
    },
    "options": [
      {
        "id": "accept_refugees",
        "text": "Grant them sanctuary.",
        "effects": {
          "coins": -30,
          "happiness": 15
        },
        "reaction": "We are in your debt, great one. Your name will be a blessing in our stories."
      },
      {
        "id": "turn_them_away",
        "text": "Turn them away at the border.",
        "effects": {
          "happiness": -15,
          "rebellionDelta": 5
        },
        "reaction": "Please... no. Our children. The fleet turns away, and hatred follows in its wake."
      }
    ]
  },



  {
    "id": "zorath_regent",
    "name": "Regent Viri of Zorath",
    "sprite": "viri.png",
    "text": "Overlord, Zorath stands ready. With investment, we can harden our industry or pacify the streets.",
    "conditions": {
      "requiresOwnedPlanet": "zorath"
    },
    "options": [
      {
        "id": "zorath_invest_industry",
        "text": "Invest in Zorath's forges.",
        "effects": {
          "coins": -30,
          "happiness": 5
        },
        "reaction": "Zorath will roar brighter than ever. The workers will curse the hours but love the pay."
      },
      {
        "id": "zorath_ignore",
        "text": "Zorath will manage without special treatment.",
        "effects": {
          "happiness": -5
        },
        "reaction": "As you say, overlord. Zorath will endure, but it will remember who paid the price."
      }
    ]
  },
  {
    "id": "karnax_envoy",
    "name": "Drogan of Karnax Prime",
    "sprite": "drogan.png",
    "text": "Overlord, Karnax Prime watches your rise. We could pledge our forges and fleets to your banner.",
    "conditions": {
      "requiresPlanetNotOwned": "karnax"
    },
    "options": [
      {
        "id": "karnax_join",
        "text": "Welcome Karnax into the empire.",
        "effects": {
          "addPlanetId": "karnax",
          "coins": 40,
          "happiness": 5
        },
        "reaction": "Then Karnax Prime bends the knee. Our docks and cannons now roar for you."
      },
      {
        "id": "karnax_reject",
        "text": "Refuse. Karnax is not worth the trouble.",
        "effects": {
          "happiness": -5,
          "rebellionDelta": 5
        },
        "reaction": "So be it. Karnax will remember this slight when the stars change hands."
      }
    ]
  },
  {
    "id": "elysion_ambassador",
    "name": "Lyra of Elysion Spires",
    "sprite": "lyra.png",
    "text": "Overlord, the spires of Elysion offer culture, science, and a very large tax base.",
    "conditions": {
      "requiresPlanetNotOwned": "elysion"
    },
    "options": [
      {
        "id": "elysion_join",
        "text": "Fold Elysion into the empire.",
        "effects": {
          "addPlanetId": "elysion",
          "happiness": 10
        },
        "reaction": "Then the spires will shine in your colors. Our scholars already debate how to praise you."
      },
      {
        "id": "elysion_reject",
        "text": "Decline. Their decadence annoys me.",
        "effects": {
          "happiness": -10,
          "rebellionDelta": 5
        },
        "reaction": "Decadent or not, overlord, our influence is vast. You may find our doors closed next time."
      }
    ]
  },
  {
    "id": "vorath_envoy",
    "name": "Forge-Lord Kor of Vorath",
    "sprite": "kor.png",
    "text": "Overlord, Vorath Forge offers raw power. We build weapons that rewrite battlefields.",
    "conditions": {
      "requiresPlanetNotOwned": "vorath"
    },
    "options": [
      {
        "id": "vorath_join",
        "text": "Bring Vorath into the war machine.",
        "effects": {
          "addPlanetId": "vorath",
          "coins": 30
        },
        "reaction": "Then our anvils sing for you. Every hammer blow will echo your name."
      },
      {
        "id": "vorath_reject",
        "text": "I do not need Vorath.",
        "effects": {
          "happiness": -5,
          "rebellionDelta": 5
        },
        "reaction": "You will when the next war comes, overlord. Remember who you turned away."
      }
    ]
  },
  {
    "id": "nyxia_envoy",
    "name": "Shade-Queen Nyx of Nyxia Veil",
    "sprite": "nyx.png",
    "text": "Overlord, Nyxia Veil has spies in every court. Let us serve, and secrets will flow to you.",
    "conditions": {
      "requiresPlanetNotOwned": "nyxia"
    },
    "options": [
      {
        "id": "nyxia_join",
        "text": "Accept Nyxia's allegiance.",
        "effects": {
          "addPlanetId": "nyxia",
          "rebellionDelta": -10
        },
        "reaction": "The Veil closes around your enemies. They will never see you coming again."
      },
      {
        "id": "nyxia_reject",
        "text": "I do not deal in shadows.",
        "effects": {
          "rebellionDelta": 10
        },
        "reaction": "Then you will be surprised often, overlord. Secrets resent being ignored."
      }
    ]
  },
  {
    "id": "talora_envoy",
    "name": "Chancellor Talen of Talora Rings",
    "sprite": "talen.png",
    "text": "Overlord, the trade lanes of Talora Rings could enrich your coffers many times over.",
    "conditions": {
      "requiresPlanetNotOwned": "talora"
    },
    "options": [
      {
        "id": "talora_join",
        "text": "Bring Talora into the fold.",
        "effects": {
          "addPlanetId": "talora",
          "coins": 25,
          "happiness": 5
        },
        "reaction": "Then every ship that circles our rings will toast your rule."
      },
      {
        "id": "talora_reject",
        "text": "Turn them away. I will take what I need elsewhere.",
        "effects": {
          "happiness": -5,
          "rebellionDelta": 5
        },
        "reaction": "Trade finds new routes, overlord. Just pray those routes do not lead to your enemies."
      }
    ]
  }
]
